cdef_converter/__init__.py
cdef_converter/__main__.py
cdef_converter/cli.py
cdef_converter/config.py
cdef_converter/exceptions.py
cdef_converter/file_processing.py
cdef_converter/logging_config.py
cdef_converter/main.py
cdef_converter/progress.py
cdef_converter/utils.py
cdef_converter-0.5.0.dist-info/METADATA
cdef_converter-0.5.0.dist-info/WHEEL
cdef_converter-0.5.0.dist-info/entry_points.txt
cdef_converter-0.5.0.dist-info/licenses/LICENSE.txt
cdef_converter-0.5.0.dist-info/RECORD
