Metadata-Version: 2.3
Name: cdef-converter
Version: 0.5.0
Summary: Add your description here
Author-email: Tobias Kragholm <50784887+tkragholm@users.noreply.github.com>
License: MIT
License-File: LICENSE.txt
Requires-Python: >=3.12
Requires-Dist: charset-normalizer[unicode-backport]>=3.3.2
Requires-Dist: polars[all]>=1.9.0
Requires-Dist: pyarrow>=17.0.0
Requires-Dist: rich>=13.9.2
Requires-Dist: tqdm>=4.66.5
Requires-Dist: typer>=0.12.5
